financial_model_taiwan/Custom_Transformers.py
financial_model_taiwan/Data_Resampling.py
financial_model_taiwan/Model_arch.py
financial_model_taiwan/Orchestrator.py
financial_model_taiwan/__init__.py
financial_model_taiwan/data_preprocessing.py
financial_model_taiwan/model_evaluation.py
financial_model_taiwan/model_training.py
financial_model_taiwan/utils.py
financial_model_taiwan/config/config.yaml
financial_model_taiwan-1.0.3.dist-info/LICENSE
financial_model_taiwan-1.0.3.dist-info/METADATA
financial_model_taiwan-1.0.3.dist-info/WHEEL
financial_model_taiwan-1.0.3.dist-info/top_level.txt
financial_model_taiwan-1.0.3.dist-info/RECORD
