Metadata-Version: 2.1
Name: financial_model_taiwan
Version: 1.0.3
Summary: A financial model package trained on data from Taiwan fiscal year 1999-2009
Home-page: https://github.com/GrimmXoXo/Deployment_Financial_Model
Author: Gaurav M
Author-email: grimmxoxo2001@example.com
Classifier: Programming Language :: Python :: 3
Classifier: License :: OSI Approved :: MIT License
Classifier: Operating System :: OS Independent
Requires-Python: >=3.6
License-File: LICENSE
Requires-Dist: pandas
Requires-Dist: numpy
Requires-Dist: joblib
Requires-Dist: optuna
Requires-Dist: pathlib
Requires-Dist: imblearn
Requires-Dist: typing
Requires-Dist: xgboost
Requires-Dist: pytest
Requires-Dist: scikit-learn
